benchbuild/__init__.py
benchbuild/command.py
benchbuild/container.py
benchbuild/driver.py
benchbuild/engine.py
benchbuild/experiment.py
benchbuild/likwid.py
benchbuild/plugins.py
benchbuild/project.py
benchbuild/settings.py
benchbuild/signals.py
benchbuild/statistics.py
benchbuild/cli/__init__.py
benchbuild/cli/bootstrap.py
benchbuild/cli/config.py
benchbuild/cli/experiment.py
benchbuild/cli/log.py
benchbuild/cli/main.py
benchbuild/cli/project.py
benchbuild/cli/run.py
benchbuild/cli/slurm.py
benchbuild/db/__init__.py
benchbuild/db/manage.py
benchbuild/db/migrate.cfg
benchbuild/db/versions/001_Remove_RegressionTest_table.py
benchbuild/db/versions/002_Remove_GlobalConfig_table.py
benchbuild/db/versions/003_Unmanage_Events.py
benchbuild/db/versions/__init__.py
benchbuild/environments/__init__.py
benchbuild/environments/bootstrap.py
benchbuild/environments/adapters/__init__.py
benchbuild/environments/adapters/buildah.py
benchbuild/environments/adapters/common.py
benchbuild/environments/adapters/podman.py
benchbuild/environments/domain/__init__.py
benchbuild/environments/domain/commands.py
benchbuild/environments/domain/declarative.py
benchbuild/environments/domain/events.py
benchbuild/environments/domain/model.py
benchbuild/environments/entrypoints/__init__.py
benchbuild/environments/entrypoints/cli.py
benchbuild/environments/service_layer/__init__.py
benchbuild/environments/service_layer/debug.py
benchbuild/environments/service_layer/ensure.py
benchbuild/environments/service_layer/handlers.py
benchbuild/environments/service_layer/messagebus.py
benchbuild/environments/service_layer/ui.py
benchbuild/environments/service_layer/unit_of_work.py
benchbuild/experiments/__init__.py
benchbuild/experiments/empty.py
benchbuild/experiments/raw.py
benchbuild/extensions/__init__.py
benchbuild/extensions/base.py
benchbuild/extensions/compiler.py
benchbuild/extensions/log.py
benchbuild/extensions/run.py
benchbuild/extensions/time.py
benchbuild/projects/__init__.py
benchbuild-6.8.dist-info/LICENSE.txt
benchbuild-6.8.dist-info/METADATA
benchbuild-6.8.dist-info/WHEEL
benchbuild-6.8.dist-info/entry_points.txt
benchbuild-6.8.dist-info/top_level.txt
benchbuild-6.8.dist-info/RECORD
