Metadata-Version: 2.1
Name: benchbuild
Version: 6.8
Summary: This is the experiment driver for the benchbuild study
Home-page: https://github.com/PolyJIT/benchbuild
Author: Andreas Simbuerger
Author-email: simbuerg@fim.uni-passau.de
License: MIT
Keywords: benchbuild experiments run-time
Classifier: Development Status :: 4 - Beta
Classifier: Intended Audience :: Developers
Classifier: Topic :: Software Development :: Testing
Classifier: License :: OSI Approved :: MIT License
Classifier: Programming Language :: Python :: 3
License-File: LICENSE.txt
Requires-Dist: Jinja2 >=3
Requires-Dist: PyYAML >=6
Requires-Dist: attrs >=22
Requires-Dist: dill >=0
Requires-Dist: pathos >=0.3
Requires-Dist: parse >=1
Requires-Dist: plumbum >=1
Requires-Dist: psutil >=5
Requires-Dist: psycopg2-binary >=2
Requires-Dist: pygit2 >=1
Requires-Dist: pygtrie >=2
Requires-Dist: pyparsing >=3
Requires-Dist: rich >=13
Requires-Dist: SQLAlchemy >=2
Requires-Dist: typing-extensions >=4
Requires-Dist: virtualenv >=20
Requires-Dist: schema >=0
Requires-Dist: result >=0
